README.rst
setup.py
PyQRCode.egg-info/PKG-INFO
PyQRCode.egg-info/SOURCES.txt
PyQRCode.egg-info/dependency_links.txt
PyQRCode.egg-info/requires.txt
PyQRCode.egg-info/top_level.txt
pyqrcode/__init__.py
pyqrcode/builder.py
pyqrcode/tables.py